itic/__init__.py
itic/__main__.py
itic/itic.py
itic-0.0.1.dist-info/LICENSE
itic-0.0.1.dist-info/METADATA
itic-0.0.1.dist-info/WHEEL
itic-0.0.1.dist-info/entry_points.txt
itic-0.0.1.dist-info/top_level.txt
itic-0.0.1.dist-info/RECORD
