Metadata-Version: 2.1
Name: itic
Version: 0.0.1
Summary: ITIC app.
Home-page: https://github.com/wmramadan/itic
Author: Wael Ramadan
Author-email: wamramadan@gmail.com
Maintainer: Wael Ramadan
Maintainer-email: wamramadan@gmail.com
License: License :: OSI Approved :: MIT License
Keywords: image to image converter
Platform: UNKNOWN
Classifier: License :: OSI Approved :: MIT License
Classifier: Environment :: Console
Classifier: Development Status :: 3 - Alpha
Classifier: Intended Audience :: Other Audience
Classifier: Operating System :: OS Independent
Classifier: Programming Language :: Python :: 3.9
Classifier: Programming Language :: Python :: 3.10
Classifier: Programming Language :: Python :: 3.11
Classifier: Topic :: Multimedia :: Graphics :: Graphics Conversion
Classifier: Topic :: Utilities
Classifier: Typing :: Typed
Requires-Python: >=3.9
License-File: LICENSE
Requires-Dist: pillow (==9.0.1)
Requires-Dist: rich (==12.6.0)
Requires-Dist: typer (==0.3.2)
